ACID_code/ACID.py
ACID_code/LSD_func_faster.py
ACID_code/__init__.py
ACID_code-0.1.0.dist-info/LICENSE
ACID_code-0.1.0.dist-info/METADATA
ACID_code-0.1.0.dist-info/WHEEL
ACID_code-0.1.0.dist-info/top_level.txt
ACID_code-0.1.0.dist-info/RECORD
