Metadata-Version: 2.1
Name: ACID-code
Version: 0.1.0
Summary: Returns line profiles from input spectra by fitting the stellar continuum and performing LSD
License-File: LICENSE
Requires-Dist: numpy
Requires-Dist: emcee
Requires-Dist: matplotlib
Requires-Dist: scipy
Requires-Dist: astropy
Requires-Dist: statistics
Requires-Dist: sphinx-rtd-theme
Requires-Dist: tqdm
